griffin_powermate/griffin_powermate.py
griffin_powermate/__init__.py
griffin_powermate-1.0.2.dist-info/DESCRIPTION.rst
griffin_powermate-1.0.2.dist-info/METADATA
griffin_powermate-1.0.2.dist-info/metadata.json
griffin_powermate-1.0.2.dist-info/RECORD
griffin_powermate-1.0.2.dist-info/top_level.txt
griffin_powermate-1.0.2.dist-info/WHEEL
