Metadata-Version: 2.0
Name: griffin-powermate
Version: 1.0.2
Summary: A simple library to use the Griffin Powermate on Windows
Home-page: https://github.com/crash7/griffin-powermate
Author: Christian Musa
Author-email: christianmusa@gmail.com
License: MIT
Keywords: griffin powermate development
Platform: UNKNOWN
Classifier: Development Status :: 5 - Production/Stable
Classifier: Intended Audience :: Developers
Classifier: Topic :: Software Development :: Build Tools
Classifier: License :: OSI Approved :: MIT License
Classifier: Programming Language :: Python :: 2
Classifier: Programming Language :: Python :: 2.7
Requires-Dist: pywinusb
